napari_nd_cropper/__init__.py
napari_nd_cropper/_dock_widget.py
napari_nd_cropper/utils.py
napari_nd_cropper-0.1.3.dist-info/LICENSE
napari_nd_cropper-0.1.3.dist-info/METADATA
napari_nd_cropper-0.1.3.dist-info/WHEEL
napari_nd_cropper-0.1.3.dist-info/entry_points.txt
napari_nd_cropper-0.1.3.dist-info/top_level.txt
napari_nd_cropper-0.1.3.dist-info/RECORD
