Metadata-Version: 2.1
Name: napari-nd-cropper
Version: 0.1.3
Summary: A napari plugin in order to crop nd-images via different modes
Home-page: https://github.com/MBPhys/napari-nd-cropper
Author: Marc Boucsein, Robin Koch
License: BSD-3-Clause
Project-URL: Bug Tracker, https://github.com/MBPhys/napari-nd-cropper/issues
Project-URL: Documentation, https://github.com/MBPhys/napari-nd-cropper
Project-URL: Source Code, https://github.com/MBPhys/napari-nd-cropper
Project-URL: User Support, https://github.com/MBPhys/napari-nd-cropper/issues
Platform: UNKNOWN
Classifier: Development Status :: 3 - Alpha
Classifier: Intended Audience :: Science/Research
Classifier: Framework :: napari
Classifier: Topic :: Software Development :: Testing
Classifier: Programming Language :: Python
Classifier: Programming Language :: Python :: 3
Classifier: Programming Language :: Python :: 3.9
Classifier: Operating System :: OS Independent
Classifier: License :: OSI Approved :: BSD License
Requires-Python: >=3.9
License-File: LICENSE
Requires-Dist: napari-plugin-engine (>=0.1.4)
Requires-Dist: numpy
Requires-Dist: napari-tools-menu
Requires-Dist: qtpy
Requires-Dist: superqt
Requires-Dist: magicgui
